Workbook

Sheet VAT Summary
H1: VAT return
J2: Period: Q1_2026
A5: Description Tax base amount VAT rate VAT amount
A7: Local sales | B7: box01 | F7: box02 | G7: 0.04 | H7: box03
B8: box04 | F8: box05 | G8: 0.1 | H8: box06
B9: box07 | C9: =(SUMIFS('Overall VAT Comparison'!$L:$L,'Overall VAT Comparison'!$A:$A,"Credit note",'Overall VAT Comparison'!$K:$K,"ES_REG/DSG_21"))*-1 | F9: box08 | G9: 0.21 | H9: box09 | I9: =(SUMIFS('Overall VAT Comparison'!$M:$M,'Overall VAT Comparison'!$A:$A,"Credit note",'Overall VAT Comparison'!$K:$K,"ES_REG/DSG_21"))*-1
A10: Intra-community acquisitions of goods and services | B10: box10 | C10: =SUMIFS('Overall VAT Comparison'!$L:$L,'Overall VAT Comparison'!$H:$H,"JOHNSON ELECTRIC POLAND SP ZOO",'Overall VAT Comparison'!$K:$K,"ES_REG/ES_ICAG_21_RCR") | H10: box11 | I10: =SUMIFS('Overall VAT Comparison'!$M:$M,'Overall VAT Comparison'!$H:$H,"JOHNSON ELECTRIC POLAND SP ZOO",'Overall VAT Comparison'!$K:$K,"ES_REG/ES_ICAG_21_RCR")
A11: Other reverse charge transactions(except ICA) | B11: box12 | H11: box13
A12: Modified taxable basis and VATamounts | B12: box14 | C12: =(SUMIFS('Overall VAT Comparison'!$L:$L,'Overall VAT Comparison'!$A:$A,"Invoice",'Overall VAT Comparison'!$K:$K,"ES_REG/DSG_21"))*-1 | H12: box15 | I12: =(SUMIFS('Overall VAT Comparison'!$M:$M,'Overall VAT Comparison'!$A:$A,"Invoice",'Overall VAT Comparison'!$K:$K,"ES_REG/DSG_21"))*-1
A13: Special retail scheme | B13: box16 | F13: box17 | H13: box18
B14: box19 | F14: box20 | G14: 0.014 | H14: box21
B15: box22 | F15: box23 | G15: 0.052 | H15: box24
A16: Modified taxable basis and VAT amounts for the special retail scheme | B16: box25 | H16: box26
A17: Total VAT payable | H17: box27 | I17: =SUM(I7:K16)
A19: Domestic purchases of goods and services | B19: box28 | H19: box29
A20: Domestic purchases of investment goods | B20: box30 | H20: box31
A21: Imports of goods | B21: box32 | H21: box33
A22: Imports of investment goods | B22: box34 | H22: box35
A23: Intra-community acquisition of goods and services | B23: box36 | C23: =C10 | H23: box37 | I23: =I10
A24: Intra-community acquisition of investment goods | B24: box38 | H24: box39
A25: Correction of deductions | B25: box40 | H25: box41
H26: box42
H27: box43
H28: box44
A29: Total VAT deductible | H29: box45 | I29: =SUM(I19:K28)
A30: VAT balance | H30: box46 | I30: =I17-I29
A32: Intra-Community supply of goods and services | H32: box59
A33: Export and deemed export transactions | H33: box60
A34: Local sales subject to reverse charge | H34: box122 | I34: =SUMIFS('Overall VAT Comparison'!$L:$L,'Overall VAT Comparison'!$K:$K,"ES_REG/ES_DSG_0_RC")
A36: Sum of results | H36: box64 | I36: =I17-I29
A37: VAT payable/credit to the State | F37: box65 | G37: 1 | H37: box66 | I37: =I17-I29
A38: VAT on importation declared to the customs uponentry | H38: box77
A39: Carried forward from previous period | H39: box110
A40: Carried forward used in this period | H40: box78
A41: Carriedforward for the future periods | H41: box87
A42: Total VAT amount | H42: box69 | I42: =I37+I38-I40
A44: VAT amount to be paid/ reclaimed | H44: box71 | I44: =I37+I38-I40

Sheet Overall VAT Comparison
A1: Doc type | B1: Invoice No. | C1: Invoice Date | D1: Registered Date / Invoice Creation Date: | E1: Delivery Date | F1: Incoterm | G1: Customer/Supplier No | H1: Customer/Supplier | I1: Our Tax Registration No. | J1: VAT Registration No. | K1: Tax Code | L1: Taxable Amt (Tax Curr) | M1: Recoverable Amt (Tax Curr) | N1: Func Total | O1: Inv Curr | P1: VAT rate % | Q1: Mapping | R1: Comments | S1: VAT Status
A2: Credit note | B2: 283268200004 | C2: 46063 | D2: 46063 | E2: 46062 | F2: DAP | G2: 70590 | H2: HUF ESPANA S.A. | I2: ESW0394952F | J2: ES A08806812 | K2: ES_REG/DSG_21 | L2: -928 | M2: -194.88 | N2: 0 | O2: EUR | P2: 21 | Q2: Domestic sale of Goods | R2: (Johnson -Corp-Common-Creditors & Accr \- VAT / -External-NL VAT Payable-Default_283-00-0000-32310000-000-46685-000)_Value Not Matching | S2: =IFERROR(VLOOKUP(TRIM(J2),'VAT Validation'!A:B,2,FALSE),"")
A3: Credit note | B3: 283268200007 | C3: 46076 | D3: 46076 | E3: 46076 | F3: DDP | G3: 33644 | H3: ERMEC S.L. | I3: ESW0394952F | K3: ES_REG/DSG_21 | L3: -8000 | M3: -1680 | N3: -1680 | O3: EUR | P3: 21 | Q3: Domestic sale of Goods | R3: Okay-Value Matching | S3: =IFERROR(VLOOKUP(TRIM(J3),'VAT Validation'!A:B,2,FALSE),"")
A4: Credit note | B4: 283268200005 | C4: 46069 | D4: 46069 | E4: 46069 | F4: DDP | G4: 11674 | H4: REPA IBERIA SLU | I4: ESW0394952F | K4: ES_REG/DSG_21 | L4: -14421 | M4: -3028.41 | N4: -3028.41 | O4: EUR | P4: 21 | Q4: Domestic sale of Goods | R4: Okay-Value Matching | S4: =IFERROR(VLOOKUP(TRIM(J4),'VAT Validation'!A:B,2,FALSE),"")
A5: Credit note | B5: 283268200003 | C5: 46056 | D5: 46056 | E5: 46051 | F5: DDP | G5: 35184 | H5: CLR COMPANIA LEVANTINA DE REDUCTORES | I5: ESW0394952F | J5: ESB03933835 | K5: ES_REG/DSG_21 | L5: -3985.92 | M5: -837.04 | N5: 0 | O5: EUR | P5: 21 | Q5: Domestic sale of Goods | R5: (Johnson -Corp-Common-Creditors & Accr \- VAT / -External-NL VAT Payable-Default_283-00-0000-32310000-000-46685-000)_Value Not Matching | S5: =IFERROR(VLOOKUP(TRIM(J5),'VAT Validation'!A:B,2,FALSE),"")
A6: Credit note | B6: 283268200009 | C6: 46077 | D6: 46077 | E6: 46077 | F6: DDP | G6: 11674 | H6: REPA IBERIA SLU | I6: ESW0394952F | K6: ES_REG/DSG_21 | L6: -3710 | M6: -779.1 | N6: -779.1 | O6: EUR | P6: 21 | Q6: Domestic sale of Goods | R6: Okay-Value Matching | S6: =IFERROR(VLOOKUP(TRIM(J6),'VAT Validation'!A:B,2,FALSE),"")
A7: Credit note | B7: 283268200008 | C7: 46076 | D7: 46076 | E7: 46073 | F7: DDP | G7: 70272 | H7: OCTÉ ELECTRIC, S.A.U. | I7: ESW0394952F | J7: ESA20025136 | K7: ES_REG/DSG_21 | L7: -13050 | M7: -2740.5 | N7: -2740.5 | O7: EUR | P7: 21 | Q7: Domestic sale of Goods | R7: Okay-Value Matching | S7: =IFERROR(VLOOKUP(TRIM(J7),'VAT Validation'!A:B,2,FALSE),"")
A8: Credit note | B8: 283268200002 | C8: 46056 | D8: 46056 | E8: 46050 | F8: DDP | G8: 35184 | H8: CLR COMPANIA LEVANTINA DE REDUCTORES | I8: ESW0394952F | J8: ESB03933835 | K8: ES_REG/DSG_21 | L8: -3985.92 | M8: -837.04 | N8: 0 | O8: EUR | P8: 21 | Q8: Domestic sale of Goods | R8: (Johnson -Corp-Common-Creditors & Accr \- VAT / -External-NL VAT Payable-Default_283-00-0000-32310000-000-46685-000)_Value Not Matching | S8: =IFERROR(VLOOKUP(TRIM(J8),'VAT Validation'!A:B,2,FALSE),"")
A9: Credit note | B9: 283268200006 | C9: 46073 | D9: 46073 | E9: 46073 | F9: DDP | G9: 11674 | H9: REPA IBERIA SLU | I9: ESW0394952F | K9: ES_REG/DSG_21 | L9: -12640.8 | M9: -2654.57 | N9: -2654.57 | O9: EUR | P9: 21 | Q9: Domestic sale of Goods | R9: Okay-Value Matching | S9: =IFERROR(VLOOKUP(TRIM(J9),'VAT Validation'!A:B,2,FALSE),"")
A10: Invoice | B10: 269265003804 | C10: 46073 | D10: 46077 | G10: 608760 | H10: JOHNSON ELECTRIC POLAND SP ZOO | I10: ESW0394952F | J10: PL6443245867 | K10: ES_REG/ES_ICAG_21_RCR | L10: 10073.78 | M10: 2115.5 | N10: 2115.5 | O10: EUR | P10: 21 | Q10: Intra community acquisition of goods - Reverse charge Recoverable | R10: Okay-Value Matching | S10: =IFERROR(VLOOKUP(TRIM(J10),'VAT Validation'!A:B,2,FALSE),"")
A11: Invoice | B11: 269265003804 | C11: 46073 | D11: 46077 | G11: 608760 | H11: JOHNSON ELECTRIC POLAND SP ZOO | I11: ESW0394952F | J11: PL6443245867 | K11: ES_REG/ES_ICAG_21_RCP | L11: 0 | M11: -2115.5 | N11: -2115.5 | O11: EUR | P11: 0 | Q11: Intra community acquisition of goods- Reverse charge payable | R11: Okay-Value Matching | S11: =IFERROR(VLOOKUP(TRIM(J11),'VAT Validation'!A:B,2,FALSE),"")
A12: Invoice | B12: 269265003817 | C12: 46073 | D12: 46077 | G12: 608760 | H12: JOHNSON ELECTRIC POLAND SP ZOO | I12: ESW0394952F | J12: PL6443245867 | K12: ES_REG/ES_ICAG_21_RCR | L12: 8284.79 | M12: 1739.81 | N12: 1739.81 | O12: EUR | P12: 21 | Q12: Intra community acquisition of goods - Reverse charge Recoverable | R12: Okay-Value Matching | S12: =IFERROR(VLOOKUP(TRIM(J12),'VAT Validation'!A:B,2,FALSE),"")
A13: Invoice | B13: 269265003830 | C13: 46076 | D13: 46077 | G13: 608760 | H13: JOHNSON ELECTRIC POLAND SP ZOO | I13: ESW0394952F | J13: PL6443245867 | K13: ES_REG/ES_ICAG_21_RCR | L13: 6737 | M13: 1414.77 | N13: 1414.77 | O13: EUR | P13: 21 | Q13: Intra community acquisition of goods - Reverse charge Recoverable | R13: Okay-Value Matching | S13: =IFERROR(VLOOKUP(TRIM(J13),'VAT Validation'!A:B,2,FALSE),"")
A14: Invoice | B14: 269265003830 | C14: 46076 | D14: 46077 | G14: 608760 | H14: JOHNSON ELECTRIC POLAND SP ZOO | I14: ESW0394952F | J14: PL6443245867 | K14: ES_REG/ES_ICAG_21_RCP | L14: 0 | M14: -1414.77 | N14: -1414.77 | O14: EUR | P14: 0 | Q14: Intra community acquisition of goods- Reverse charge payable | R14: Okay-Value Matching | S14: =IFERROR(VLOOKUP(TRIM(J14),'VAT Validation'!A:B,2,FALSE),"")
A15: Invoice | B15: 269265003078 | C15: 46062 | D15: 46077 | G15: 608760 | H15: JOHNSON ELECTRIC POLAND SP ZOO | I15: ESW0394952F | J15: PL6443245867 | K15: ES_REG/ES_ICAG_21_RCP | L15: 0 | M15: -210.68 | N15: -210.68 | O15: EUR | P15: 0 | Q15: Intra community acquisition of goods- Reverse charge payable | R15: Okay-Value Matching | S15: =IFERROR(VLOOKUP(TRIM(J15),'VAT Validation'!A:B,2,FALSE),"")
A16: Invoice | B16: 269265003155 | C16: 46069 | D16: 46077 | G16: 608760 | H16: JOHNSON ELECTRIC POLAND SP ZOO | I16: ESW0394952F | J16: PL6443245867 | K16: ES_REG/ES_ICAG_21_RCR | L16: 9789.82 | M16: 2055.86 | N16: 2055.86 | O16: EUR | P16: 21 | Q16: Intra community acquisition of goods - Reverse charge Recoverable | R16: Okay-Value Matching | S16: =IFERROR(VLOOKUP(TRIM(J16),'VAT Validation'!A:B,2,FALSE),"")
A17: Invoice | B17: 269265003155 | C17: 46069 | D17: 46077 | G17: 608760 | H17: JOHNSON ELECTRIC POLAND SP ZOO | I17: ESW0394952F | J17: PL6443245867 | K17: ES_REG/ES_ICAG_21_RCP | L17: 0 | M17: -2055.86 | N17: -2055.86 | O17: EUR | P17: 0 | Q17: Intra community acquisition of goods- Reverse charge payable | R17: Okay-Value Matching | S17: =IFERROR(VLOOKUP(TRIM(J17),'VAT Validation'!A:B,2,FALSE),"")
A18: Invoice | B18: 269265003817 | C18: 46073 | D18: 46077 | G18: 608760 | H18: JOHNSON ELECTRIC POLAND SP ZOO | I18: ESW0394952F | J18: PL6443245867 | K18: ES_REG/ES_ICAG_21_RCP | L18: 0 | M18: -1739.81 | N18: -1739.81 | O18: EUR | P18: 0 | Q18: Intra community acquisition of goods- Reverse charge payable | R18: Okay-Value Matching | S18: =IFERROR(VLOOKUP(TRIM(J18),'VAT Validation'!A:B,2,FALSE),"")
A19: Invoice | B19: 269265003843 | C19: 46077 | D19: 46078 | G19: 608760 | H19: JOHNSON ELECTRIC POLAND SP ZOO | I19: ESW0394952F | J19: PL6443245867 | K19: ES_REG/ES_ICAG_21_RCP | L19: 0 | M19: -274.96 | N19: -274.96 | O19: EUR | P19: 0 | Q19: Intra community acquisition of goods- Reverse charge payable | R19: Okay-Value Matching | S19: =IFERROR(VLOOKUP(TRIM(J19),'VAT Validation'!A:B,2,FALSE),"")
A20: Invoice | B20: 269265003078 | C20: 46062 | D20: 46077 | G20: 608760 | H20: JOHNSON ELECTRIC POLAND SP ZOO | I20: ESW0394952F | J20: PL6443245867 | K20: ES_REG/ES_ICAG_21_RCR | L20: 1003.26 | M20: 210.68 | N20: 210.68 | O20: EUR | P20: 21 | Q20: Intra community acquisition of goods - Reverse charge Recoverable | R20: Okay-Value Matching | S20: =IFERROR(VLOOKUP(TRIM(J20),'VAT Validation'!A:B,2,FALSE),"")
A21: Invoice | B21: 269265003843 | C21: 46077 | D21: 46078 | G21: 608760 | H21: JOHNSON ELECTRIC POLAND SP ZOO | I21: ESW0394952F | J21: PL6443245867 | K21: ES_REG/ES_ICAG_21_RCR | L21: 1309.35 | M21: 274.96 | N21: 274.96 | O21: EUR | P21: 21 | Q21: Intra community acquisition of goods - Reverse charge Recoverable | R21: Okay-Value Matching | S21: =IFERROR(VLOOKUP(TRIM(J21),'VAT Validation'!A:B,2,FALSE),"")
A22: Credit note | B22: 283268200010 | C22: 46108 | D22: 46108 | E22: 46108 | F22: DDP | G22: 11674 | H22: REPA IBERIA SLU | I22: ESW0394952F | K22: ES_REG/DSG_21 | L22: -8904 | M22: -1869.84 | N22: -1869.84 | O22: EUR | P22: 21 | Q22: Domestic sale of Goods | R22: Okay-Value Matching | S22: =IFERROR(VLOOKUP(TRIM(J22),'VAT Validation'!A:B,2,FALSE),"")
A23: Invoice | B23: 269265004161 | C23: 46108 | D23: 46111 | G23: 608760 | H23: JOHNSON ELECTRIC POLAND SP ZOO | I23: ESW0394952F | J23: PL6443245867 | K23: ES_REG/ES_ICAG_21_RCP | L23: 0 | M23: -659.91 | N23: -659.91 | O23: EUR | P23: 0 | Q23: Intra community acquisition of goods- Reverse charge payable | R23: Okay-Value Matching | S23: =IFERROR(VLOOKUP(TRIM(J23),'VAT Validation'!A:B,2,FALSE),"")
A24: Invoice | B24: 269265004054 | C24: 46098 | D24: 46101 | G24: 608760 | H24: JOHNSON ELECTRIC POLAND SP ZOO | I24: ESW0394952F | J24: PL6443245867 | K24: ES_REG/ES_ICAG_21_RCR | L24: 3405.84 | M24: 715.23 | N24: 715.23 | O24: EUR | P24: 21 | Q24: Intra community acquisition of goods - Reverse charge Recoverable | R24: Okay-Value Matching | S24: =IFERROR(VLOOKUP(TRIM(J24),'VAT Validation'!A:B,2,FALSE),"")
A25: Invoice | B25: 269265004072 | C25: 46099 | D25: 46101 | G25: 608760 | H25: JOHNSON ELECTRIC POLAND SP ZOO | I25: ESW0394952F | J25: PL6443245867 | K25: ES_REG/ES_ICAG_21_RCP | L25: 0 | M25: -715.23 | N25: -715.23 | O25: EUR | P25: 0 | Q25: Intra community acquisition of goods- Reverse charge payable | R25: Okay-Value Matching | S25: =IFERROR(VLOOKUP(TRIM(J25),'VAT Validation'!A:B,2,FALSE),"")
A26: Invoice | B26: 269265004161 | C26: 46108 | D26: 46111 | G26: 608760 | H26: JOHNSON ELECTRIC POLAND SP ZOO | I26: ESW0394952F | J26: PL6443245867 | K26: ES_REG/ES_ICAG_21_RCR | L26: 3142.45 | M26: 659.91 | N26: 659.91 | O26: EUR | P26: 21 | Q26: Intra community acquisition of goods - Reverse charge Recoverable | R26: Okay-Value Matching | S26: =IFERROR(VLOOKUP(TRIM(J26),'VAT Validation'!A:B,2,FALSE),"")
A27: Invoice | B27: 269265004054 | C27: 46098 | D27: 46101 | G27: 608760 | H27: JOHNSON ELECTRIC POLAND SP ZOO | I27: ESW0394952F | J27: PL6443245867 | K27: ES_REG/ES_ICAG_21_RCP | L27: 0 | M27: -715.23 | N27: -715.23 | O27: EUR | P27: 0 | Q27: Intra community acquisition of goods- Reverse charge payable | R27: Okay-Value Matching | S27: =IFERROR(VLOOKUP(TRIM(J27),'VAT Validation'!A:B,2,FALSE),"")
A28: Invoice | B28: 269265004072 | C28: 46099 | D28: 46101 | G28: 608760 | H28: JOHNSON ELECTRIC POLAND SP ZOO | I28: ESW0394952F | J28: PL6443245867 | K28: ES_REG/ES_ICAG_21_RCR | L28: 3405.84 | M28: 715.23 | N28: 715.23 | O28: EUR | P28: 21 | Q28: Intra community acquisition of goods - Reverse charge Recoverable | R28: Okay-Value Matching | S28: =IFERROR(VLOOKUP(TRIM(J28),'VAT Validation'!A:B,2,FALSE),"")
A29: Credit note | B29: 283268200001 | C29: 46034 | D29: 46034 | E29: 46031 | F29: DAP | G29: 70590 | H29: HUF ESPANA S.A. | I29: ESW0394952F | J29: ES A08806812 | K29: ES_REG/DSG_21 | L29: -3628.8 | M29: -762.05 | N29: 0 | O29: EUR | P29: 21 | Q29: Domestic sale of Goods | R29: (Johnson -Corp-Common-Creditors & Accr \- VAT / -External-NL VAT Payable-Default_283-00-0000-32310000-000-46685-000)_Value Not Matching | S29: =IFERROR(VLOOKUP(TRIM(J29),'VAT Validation'!A:B,2,FALSE),"")

Sheet EC acquisition
A1: Doc type | B1: Invoice No. | C1: Invoice Date | D1: Registered Date / Invoice Creation Date: | E1: Delivery Date | F1: Incoterm | G1: Customer/Supplier No | H1: Customer/Supplier | I1: Our Tax Registration No. | J1: VAT Registration No. | K1: Tax Code | L1: Taxable Amt (Tax Curr) | M1: Recoverable Amt (Tax Curr) | N1: Func Total | O1: Inv Curr | P1: VAT rate % | Q1: Mapping | R1: Comments | S1: VAT Status
A2: Invoice | B2: 269265003804 | C2: 46073 | D2: 46077 | G2: 608760 | H2: JOHNSON ELECTRIC POLAND SP ZOO | I2: ESW0394952F | J2: PL6443245867 | K2: ES_REG/ES_ICAG_21_RCR | L2: 10073.78 | M2: 2115.5 | N2: 2115.5 | O2: EUR | P2: 21 | Q2: Intra community acquisition of goods - Reverse charge Recoverable | R2: Okay-Value Matching | S2: =IFERROR(VLOOKUP(TRIM(J2),'VAT Validation'!A:B,2,FALSE),"")
A3: Invoice | B3: 269265003817 | C3: 46073 | D3: 46077 | G3: 608760 | H3: JOHNSON ELECTRIC POLAND SP ZOO | I3: ESW0394952F | J3: PL6443245867 | K3: ES_REG/ES_ICAG_21_RCR | L3: 8284.79 | M3: 1739.81 | N3: 1739.81 | O3: EUR | P3: 21 | Q3: Intra community acquisition of goods - Reverse charge Recoverable | R3: Okay-Value Matching | S3: =IFERROR(VLOOKUP(TRIM(J3),'VAT Validation'!A:B,2,FALSE),"")
A4: Invoice | B4: 269265003830 | C4: 46076 | D4: 46077 | G4: 608760 | H4: JOHNSON ELECTRIC POLAND SP ZOO | I4: ESW0394952F | J4: PL6443245867 | K4: ES_REG/ES_ICAG_21_RCR | L4: 6737 | M4: 1414.77 | N4: 1414.77 | O4: EUR | P4: 21 | Q4: Intra community acquisition of goods - Reverse charge Recoverable | R4: Okay-Value Matching | S4: =IFERROR(VLOOKUP(TRIM(J4),'VAT Validation'!A:B,2,FALSE),"")
A5: Invoice | B5: 269265003155 | C5: 46069 | D5: 46077 | G5: 608760 | H5: JOHNSON ELECTRIC POLAND SP ZOO | I5: ESW0394952F | J5: PL6443245867 | K5: ES_REG/ES_ICAG_21_RCR | L5: 9789.82 | M5: 2055.86 | N5: 2055.86 | O5: EUR | P5: 21 | Q5: Intra community acquisition of goods - Reverse charge Recoverable | R5: Okay-Value Matching | S5: =IFERROR(VLOOKUP(TRIM(J5),'VAT Validation'!A:B,2,FALSE),"")
A6: Invoice | B6: 269265003078 | C6: 46062 | D6: 46077 | G6: 608760 | H6: JOHNSON ELECTRIC POLAND SP ZOO | I6: ESW0394952F | J6: PL6443245867 | K6: ES_REG/ES_ICAG_21_RCR | L6: 1003.26 | M6: 210.68 | N6: 210.68 | O6: EUR | P6: 21 | Q6: Intra community acquisition of goods - Reverse charge Recoverable | R6: Okay-Value Matching | S6: =IFERROR(VLOOKUP(TRIM(J6),'VAT Validation'!A:B,2,FALSE),"")
A7: Invoice | B7: 269265003843 | C7: 46077 | D7: 46078 | G7: 608760 | H7: JOHNSON ELECTRIC POLAND SP ZOO | I7: ESW0394952F | J7: PL6443245867 | K7: ES_REG/ES_ICAG_21_RCR | L7: 1309.35 | M7: 274.96 | N7: 274.96 | O7: EUR | P7: 21 | Q7: Intra community acquisition of goods - Reverse charge Recoverable | R7: Okay-Value Matching | S7: =IFERROR(VLOOKUP(TRIM(J7),'VAT Validation'!A:B,2,FALSE),"")
A8: Invoice | B8: 269265004054 | C8: 46098 | D8: 46101 | G8: 608760 | H8: JOHNSON ELECTRIC POLAND SP ZOO | I8: ESW0394952F | J8: PL6443245867 | K8: ES_REG/ES_ICAG_21_RCR | L8: 3405.84 | M8: 715.23 | N8: 715.23 | O8: EUR | P8: 21 | Q8: Intra community acquisition of goods - Reverse charge Recoverable | R8: Okay-Value Matching | S8: =IFERROR(VLOOKUP(TRIM(J8),'VAT Validation'!A:B,2,FALSE),"")
A9: Invoice | B9: 269265004161 | C9: 46108 | D9: 46111 | G9: 608760 | H9: JOHNSON ELECTRIC POLAND SP ZOO | I9: ESW0394952F | J9: PL6443245867 | K9: ES_REG/ES_ICAG_21_RCR | L9: 3142.45 | M9: 659.91 | N9: 659.91 | O9: EUR | P9: 21 | Q9: Intra community acquisition of goods - Reverse charge Recoverable | R9: Okay-Value Matching | S9: =IFERROR(VLOOKUP(TRIM(J9),'VAT Validation'!A:B,2,FALSE),"")
A10: Invoice | B10: 269265004072 | C10: 46099 | D10: 46101 | G10: 608760 | H10: JOHNSON ELECTRIC POLAND SP ZOO | I10: ESW0394952F | J10: PL6443245867 | K10: ES_REG/ES_ICAG_21_RCR | L10: 3405.84 | M10: 715.23 | N10: 715.23 | O10: EUR | P10: 21 | Q10: Intra community acquisition of goods - Reverse charge Recoverable | R10: Okay-Value Matching | S10: =IFERROR(VLOOKUP(TRIM(J10),'VAT Validation'!A:B,2,FALSE),"")

Sheet Domestic sales (21% VAT)
A1: Doc type | B1: Invoice No. | C1: Invoice Date | D1: Registered Date / Invoice Creation Date: | E1: Delivery Date | F1: Incoterm | G1: Customer/Supplier No | H1: Customer/Supplier | I1: Our Tax Registration No. | J1: VAT Registration No. | K1: Tax Code | L1: Taxable Amt (Tax Curr) | M1: Recoverable Amt (Tax Curr) | N1: Func Total | O1: Inv Curr | P1: VAT rate % | Q1: Mapping | R1: Comments | S1: VAT Status
A2: Credit note | B2: 283268200004 | C2: 46063 | D2: 46063 | E2: 46062 | F2: DAP | G2: 70590 | H2: HUF ESPANA S.A. | I2: ESW0394952F | J2: ES A08806812 | K2: ES_REG/DSG_21 | L2: -928 | M2: -194.88 | N2: 0 | O2: EUR | P2: 21 | Q2: Domestic sale of Goods | R2: (Johnson -Corp-Common-Creditors & Accr \- VAT / -External-NL VAT Payable-Default_283-00-0000-32310000-000-46685-000)_Value Not Matching | S2: =IFERROR(VLOOKUP(TRIM(J2),'VAT Validation'!A:B,2,FALSE),"")
A3: Credit note | B3: 283268200007 | C3: 46076 | D3: 46076 | E3: 46076 | F3: DDP | G3: 33644 | H3: ERMEC S.L. | I3: ESW0394952F | K3: ES_REG/DSG_21 | L3: -8000 | M3: -1680 | N3: -1680 | O3: EUR | P3: 21 | Q3: Domestic sale of Goods | R3: Okay-Value Matching | S3: =IFERROR(VLOOKUP(TRIM(J3),'VAT Validation'!A:B,2,FALSE),"")
A4: Credit note | B4: 283268200005 | C4: 46069 | D4: 46069 | E4: 46069 | F4: DDP | G4: 11674 | H4: REPA IBERIA SLU | I4: ESW0394952F | K4: ES_REG/DSG_21 | L4: -14421 | M4: -3028.41 | N4: -3028.41 | O4: EUR | P4: 21 | Q4: Domestic sale of Goods | R4: Okay-Value Matching | S4: =IFERROR(VLOOKUP(TRIM(J4),'VAT Validation'!A:B,2,FALSE),"")
A5: Credit note | B5: 283268200003 | C5: 46056 | D5: 46056 | E5: 46051 | F5: DDP | G5: 35184 | H5: CLR COMPANIA LEVANTINA DE REDUCTORES | I5: ESW0394952F | J5: ESB03933835 | K5: ES_REG/DSG_21 | L5: -3985.92 | M5: -837.04 | N5: 0 | O5: EUR | P5: 21 | Q5: Domestic sale of Goods | R5: (Johnson -Corp-Common-Creditors & Accr \- VAT / -External-NL VAT Payable-Default_283-00-0000-32310000-000-46685-000)_Value Not Matching | S5: =IFERROR(VLOOKUP(TRIM(J5),'VAT Validation'!A:B,2,FALSE),"")
A6: Credit note | B6: 283268200009 | C6: 46077 | D6: 46077 | E6: 46077 | F6: DDP | G6: 11674 | H6: REPA IBERIA SLU | I6: ESW0394952F | K6: ES_REG/DSG_21 | L6: -3710 | M6: -779.1 | N6: -779.1 | O6: EUR | P6: 21 | Q6: Domestic sale of Goods | R6: Okay-Value Matching | S6: =IFERROR(VLOOKUP(TRIM(J6),'VAT Validation'!A:B,2,FALSE),"")
A7: Credit note | B7: 283268200008 | C7: 46076 | D7: 46076 | E7: 46073 | F7: DDP | G7: 70272 | H7: OCTÉ ELECTRIC, S.A.U. | I7: ESW0394952F | J7: ESA20025136 | K7: ES_REG/DSG_21 | L7: -13050 | M7: -2740.5 | N7: -2740.5 | O7: EUR | P7: 21 | Q7: Domestic sale of Goods | R7: Okay-Value Matching | S7: =IFERROR(VLOOKUP(TRIM(J7),'VAT Validation'!A:B,2,FALSE),"")
A8: Credit note | B8: 283268200002 | C8: 46056 | D8: 46056 | E8: 46050 | F8: DDP | G8: 35184 | H8: CLR COMPANIA LEVANTINA DE REDUCTORES | I8: ESW0394952F | J8: ESB03933835 | K8: ES_REG/DSG_21 | L8: -3985.92 | M8: -837.04 | N8: 0 | O8: EUR | P8: 21 | Q8: Domestic sale of Goods | R8: (Johnson -Corp-Common-Creditors & Accr \- VAT / -External-NL VAT Payable-Default_283-00-0000-32310000-000-46685-000)_Value Not Matching | S8: =IFERROR(VLOOKUP(TRIM(J8),'VAT Validation'!A:B,2,FALSE),"")
A9: Credit note | B9: 283268200006 | C9: 46073 | D9: 46073 | E9: 46073 | F9: DDP | G9: 11674 | H9: REPA IBERIA SLU | I9: ESW0394952F | K9: ES_REG/DSG_21 | L9: -12640.8 | M9: -2654.57 | N9: -2654.57 | O9: EUR | P9: 21 | Q9: Domestic sale of Goods | R9: Okay-Value Matching | S9: =IFERROR(VLOOKUP(TRIM(J9),'VAT Validation'!A:B,2,FALSE),"")
A10: Credit note | B10: 283268200010 | C10: 46108 | D10: 46108 | E10: 46108 | F10: DDP | G10: 11674 | H10: REPA IBERIA SLU | I10: ESW0394952F | K10: ES_REG/DSG_21 | L10: -8904 | M10: -1869.84 | N10: -1869.84 | O10: EUR | P10: 21 | Q10: Domestic sale of Goods | R10: Okay-Value Matching | S10: =IFERROR(VLOOKUP(TRIM(J10),'VAT Validation'!A:B,2,FALSE),"")
A11: Credit note | B11: 283268200001 | C11: 46034 | D11: 46034 | E11: 46031 | F11: DAP | G11: 70590 | H11: HUF ESPANA S.A. | I11: ESW0394952F | J11: ES A08806812 | K11: ES_REG/DSG_21 | L11: -3628.8 | M11: -762.05 | N11: 0 | O11: EUR | P11: 21 | Q11: Domestic sale of Goods | R11: (Johnson -Corp-Common-Creditors & Accr \- VAT / -External-NL VAT Payable-Default_283-00-0000-32310000-000-46685-000)_Value Not Matching | S11: =IFERROR(VLOOKUP(TRIM(J11),'VAT Validation'!A:B,2,FALSE),"")

Sheet Domestic sales (0% VAT)
A1: Doc type | B1: Invoice No. | C1: Invoice Date | D1: Registered Date / Invoice Creation Date: | E1: Delivery Date | F1: Incoterm | G1: Customer/Supplier No | H1: Customer/Supplier | I1: Our Tax Registration No. | J1: VAT Registration No. | K1: Tax Code | L1: Taxable Amt (Tax Curr) | M1: Recoverable Amt (Tax Curr) | N1: Func Total | O1: Inv Curr | P1: VAT rate % | Q1: Mapping | R1: Comments

Sheet Missed Inv in VAT Transaction
A1: Period | B1: Account Number | C1: Account Description | D1: Journal Source | E1: Journal Batch Name | F1: Accounting Sequence | G1: Category | H1: JE Name | I1: Customer/Vendor | J1: Invoice NO. | K1: Invoice Date | L1: Posted Date | M1: Document No. | N1: PO No. | O1: Project No. | P1: Curr | Q1: Trans. Debits | R1: Trans. Credits | S1: Trans Total | T1: Func. Debits | U1: Func. Credits | V1: Func Total | W1: Description | X1: Invoice Reference Number | Y1: Journal Description | Z1: Unnamed: 25 | AA1: Unnamed: 26 | AB1: Unnamed: 27 | AC1: Unnamed: 28

Sheet VAT Validation
A1: VAT Registration No. | B1: VAT Status
A2: ES A08806812 | B2: VALID
A3: ESA20025136 | B3: VALID
A4: ESB03933835 | B4: VALID
A5: PL6443245867 | B5: VALID
